LICENSE
MANIFEST.in
README.rst
requirements.txt
setup.cfg
setup.py
djoauth2/__init__.py
djoauth2/__init__.pyc
djoauth2/access_token.py
djoauth2/access_token.pyc
djoauth2/admin.py
djoauth2/authorization.py
djoauth2/authorization.pyc
djoauth2/conf.py
djoauth2/conf.pyc
djoauth2/decorators.py
djoauth2/decorators.pyc
djoauth2/errors.py
djoauth2/errors.pyc
djoauth2/helpers.py
djoauth2/helpers.pyc
djoauth2/models.py
djoauth2/models.pyc
djoauth2/signals.py
djoauth2/signals.pyc
djoauth2/views.py
djoauth2/views.pyc
djoauth2.egg-info/PKG-INFO
djoauth2.egg-info/SOURCES.txt
djoauth2.egg-info/dependency_links.txt
djoauth2.egg-info/requires.txt
djoauth2.egg-info/top_level.txt
djoauth2/fixtures/auth_user.json
djoauth2/fixtures/djoauth2_client.json
djoauth2/fixtures/djoauth2_scope.json
djoauth2/migrations/0001_initial.py
djoauth2/migrations/__init__.py
djoauth2/templates/djoauth2/authorization.html
djoauth2/tests/__init__.py
djoauth2/tests/abstractions.py
djoauth2/tests/access_token.py
djoauth2/tests/authorization.py
djoauth2/tests/endpoint.py
djoauth2/tests/helpers.py
djoauth2/tests/test_urls.py