Metadata-Version: 1.0
Name: djoauth2
Version: 0.6.0
Summary: OAuth 2.0 server implementation.
Home-page: https://github.com/Locu/djoauth2/
Author: Locu, Inc.
Author-email: devteam@locu.com
License: MIT License
Download-URL: https://github.com/Locu/djoauth2/tarball/0.6.0
Keywords: oauth,oauth2,django
Platform: UNKNOWN
Classifier: Environment :: Web Environment
Classifier: Framework :: Django
Classifier: Intended Audience :: Developers
Classifier: License :: OSI Approved :: MIT License
Classifier: Operating System :: OS Independent
Classifier: Programming Language :: Python
Classifier: Programming Language :: Python :: 2
Classifier: Programming Language :: Python :: 2.7
